simexpal/__init__.py
simexpal/base.py
simexpal/build.py
simexpal/instances.py
simexpal/queuesock.py
simexpal/util.py
simexpal/launch/__init__.py
simexpal/launch/common.py
simexpal/launch/fork.py
simexpal/launch/queue.py
simexpal/launch/sge.py
simexpal/launch/slurm.py
simexpal/schemes/experiments.json
simexpal/schemes/launchers.json
simexpal-1.1.data/scripts/simex
simexpal-1.1.dist-info/METADATA
simexpal-1.1.dist-info/WHEEL
simexpal-1.1.dist-info/top_level.txt
simexpal-1.1.dist-info/RECORD
