Metadata-Version: 2.1
Name: simexpal
Version: 1.1
Summary: Tool to Simplify Experimental Algorithmics
Home-page: https://github.com/hu-macsy/simexpal
Author: Florian Willich
Author-email: florian.willich@informatik.hu-berlin.de
License: MIT
Requires-Dist: importlib-metadata <5.0
Requires-Dist: argcomplete
Requires-Dist: requests
Requires-Dist: pyyaml
Requires-Dist: jsonschema >=3.2.0
